setup.py
DonkeySimple/__init__.py
DonkeySimple/docs.txt
DonkeySimple.egg-info/PKG-INFO
DonkeySimple.egg-info/SOURCES.txt
DonkeySimple.egg-info/dependency_links.txt
DonkeySimple.egg-info/not-zip-safe
DonkeySimple.egg-info/requires.txt
DonkeySimple.egg-info/top_level.txt
DonkeySimple/CmdInterface/__init__.py
DonkeySimple/DS/__init__.py
DonkeySimple/DS/_common.py
DonkeySimple/DS/_controllers.py
DonkeySimple/DS/_git.py
DonkeySimple/DS/_site_generator.py
DonkeySimple/DS/_template_renderer.py
DonkeySimple/DS/download.py
DonkeySimple/DS/ds_creator.py
DonkeySimple/DS/random_string.py
DonkeySimple/DS/send_emails.py
DonkeySimple/WebInterface/__init__.py
DonkeySimple/WebInterface/_auth.py
DonkeySimple/WebInterface/_forms.py
DonkeySimple/WebInterface/_views.py
DonkeySimple/WebInterface/static/editor.js
DonkeySimple/WebInterface/static/editor_styles.css
DonkeySimple/WebInterface/static/favicon.png
DonkeySimple/WebInterface/static/signin.css
DonkeySimple/WebInterface/static/libs/bootbox.min.js
DonkeySimple/WebInterface/static/libs/bootstrap-theme.min.css
DonkeySimple/WebInterface/static/libs/bootstrap.min.css
DonkeySimple/WebInterface/static/libs/bootstrap.min.js
DonkeySimple/WebInterface/static/libs/jquery.form.min.js
DonkeySimple/WebInterface/static/libs/jquery.min.js
DonkeySimple/WebInterface/static/libs/mousetrap.min.js
DonkeySimple/WebInterface/static/libs/ace/ace.js
DonkeySimple/WebInterface/static/libs/ace/ext-chromevox.js
DonkeySimple/WebInterface/static/libs/ace/ext-elastic_tabstops_lite.js
DonkeySimple/WebInterface/static/libs/ace/ext-emmet.js
DonkeySimple/WebInterface/static/libs/ace/ext-error_marker.js
DonkeySimple/WebInterface/static/libs/ace/ext-keybinding_menu.js
DonkeySimple/WebInterface/static/libs/ace/ext-language_tools.js
DonkeySimple/WebInterface/static/libs/ace/ext-modelist.js
DonkeySimple/WebInterface/static/libs/ace/ext-old_ie.js
DonkeySimple/WebInterface/static/libs/ace/ext-options.js
DonkeySimple/WebInterface/static/libs/ace/ext-searchbox.js
DonkeySimple/WebInterface/static/libs/ace/ext-settings_menu.js
DonkeySimple/WebInterface/static/libs/ace/ext-spellcheck.js
DonkeySimple/WebInterface/static/libs/ace/ext-split.js
