Metadata-Version: 1.0
Name: DonkeySimple
Version: 0.20.02
Summary: Super Simple python system for building and deploying static websites
Home-page: https://github.com/samuelcolvin/donkey-simple
Author: Samuel Colvin
Author-email: S@muelColvin.com
License: MIT
Platform: any
